{
  "version": "2.5",
  "description": "Erlelo 2-chamber climate control - v2.5 Dual-Layer Cascade",
  "num_chambers": 2,
  "v25_features": {
    "dual_layer_cascade": true,
    "directional_hysteresis": true,
    "humidity_state_machine": true,
    "buffer_size": 5
  },
  "default_control_constants": {
    "deltahi_kamra_homerseklet": 15,
    "deltalo_kamra_homerseklet": 10,
    "temp_hysteresis_kamra": 5,
    "ah_deadzone_kamra": 80,
    "ah_hysteresis_kamra": 30,
    "deltahi_befujt_homerseklet": 10,
    "deltalo_befujt_homerseklet": 10,
    "temp_hysteresis_befujt": 3,
    "ah_deadzone_befujt": 50,
    "ah_hysteresis_befujt": 20,
    "outdoor_mix_ratio": 30,
    "outdoor_use_threshold": 50,
    "proportional_gain": 10,
    "min_supply_air_temp": 60,
    "max_supply_air_temp": 400,
    "min_temp_no_humidifier": 110,
    "buffer_size": 5,
    "spike_threshold": 50,
    "max_error_count": 10,
    "temp_change_threshold": 2,
    "humidity_change_threshold": 5,
    "humidifier_installed": false,
    "humidifier_start_delta": 50,
    "sleep_cycle_enabled": false,
    "sleep_on_minutes": 45,
    "sleep_off_minutes": 15,
    "init_duration": 32
  },
  "naming_convention": {
    "chamber_specific": "_ch1, _ch2, _ch3",
    "global": "_glbl"
  },
  "variables": [
    {
      "name": "kamra_homerseklet_ch1",
      "type": "integer",
      "default_value": 0,
      "description": "Chamber 1: Chamber temperature \u00d710"
    },
    {
      "name": "kamra_para_ch1",
      "type": "integer",
      "default_value": 0,
      "description": "Chamber 1: Chamber humidity \u00d710"
    },
    {
      "name": "kamra_homerseklet_raw_ch1",
      "type": "integer",
      "default_value": 0,
      "description": "Chamber 1: Raw chamber temperature"
    },
    {
      "name": "kamra_para_raw_ch1",
      "type": "integer",
      "default_value": 0,
      "description": "Chamber 1: Raw chamber humidity"
    },
    {
      "name": "kamra_cel_homerseklet_ch1",
      "type": "integer",
      "default_value": 150,
      "description": "Chamber 1: Target chamber temp \u00d710 (15.0\u00b0C)"
    },
    {
      "name": "kamra_cel_para_ch1",
      "type": "integer",
      "default_value": 750,
      "description": "Chamber 1: Target chamber humidity \u00d710 (75.0%)"
    },
    {
      "name": "befujt_cel_homerseklet_ch1",
      "type": "integer",
      "default_value": 0,
      "description": "Chamber 1: Calculated supply air target temp"
    },
    {
      "name": "befujt_cel_para_ch1",
      "type": "integer",
      "default_value": 0,
      "description": "Chamber 1: Calculated supply air target humidity"
    },
    {
      "name": "befujt_homerseklet_akt_ch1",
      "type": "integer",
      "default_value": 0,
      "description": "Chamber 1: Current supply air temp"
    },
    {
      "name": "befujt_para_akt_ch1",
      "type": "integer",
      "default_value": 0,
      "description": "Chamber 1: Current supply air humidity"
    },
    {
      "name": "befujt_homerseklet_raw_ch1",
      "type": "integer",
      "default_value": 0,
      "description": "Chamber 1: Raw supply air temperature"
    },
    {
      "name": "befujt_para_raw_ch1",
      "type": "integer",
      "default_value": 0,
      "description": "Chamber 1: Raw supply air humidity"
    },
    {
      "name": "befujt_homerseklet_table_ch1",
      "type": "string",
      "default_value": "[]",
      "description": "Chamber 1: Supply air temp buffer"
    },
    {
      "name": "befujt_para_table_ch1",
      "type": "string",
      "default_value": "[]",
      "description": "Chamber 1: Supply air humidity buffer"
    },
    {
      "name": "kamra_homerseklet_table_ch1",
      "type": "string",
      "default_value": "[]",
      "description": "Chamber 1: Chamber temp buffer"
    },
    {
      "name": "kamra_para_table_ch1",
      "type": "string",
      "default_value": "[]",
      "description": "Chamber 1: Chamber humidity buffer"
    },
    {
      "name": "befujt_hibaszam_ch1",
      "type": "integer",
      "default_value": 10,
      "description": "Chamber 1: Supply sensor error count"
    },
    {
      "name": "kamra_hibaszam_ch1",
      "type": "integer",
      "default_value": 10,
      "description": "Chamber 1: Chamber sensor error count"
    },
    {
      "name": "constansok_ch1",
      "type": "string",
      "default_value": "{\"deltahi_kamra_homerseklet\":15,\"deltalo_kamra_homerseklet\":10,\"temp_hysteresis_kamra\":5,\"ah_deadzone_kamra\":80,\"ah_hysteresis_kamra\":30,\"deltahi_befujt_homerseklet\":10,\"deltalo_befujt_homerseklet\":10,\"temp_hysteresis_befujt\":3,\"ah_deadzone_befujt\":50,\"ah_hysteresis_befujt\":20,\"outdoor_mix_ratio\":30,\"outdoor_use_threshold\":50,\"proportional_gain\":10,\"min_supply_air_temp\":60,\"max_supply_air_temp\":400,\"min_temp_no_humidifier\":110,\"buffer_size\":5,\"spike_threshold\":50,\"max_error_count\":10,\"temp_change_threshold\":2,\"humidity_change_threshold\":5,\"humidifier_installed\":false,\"humidifier_start_delta\":50,\"sleep_cycle_enabled\":false,\"sleep_on_minutes\":45,\"sleep_off_minutes\":15,\"init_duration\":32}",
      "description": "Chamber 1: Control constants JSON (v2.5)"
    },
    {
      "name": "signals_ch1",
      "type": "string",
      "default_value": "{}",
      "description": "Chamber 1: Control signals state"
    },
    {
      "name": "cycle_variable_ch1",
      "type": "string",
      "default_value": "{\"aktiv\":true}",
      "description": "Chamber 1: Cycle state"
    },
    {
      "name": "ah_kamra_ch1",
      "type": "integer",
      "default_value": 0,
      "description": "Chamber 1: Chamber absolute humidity \u00d71000 (mg/m\u00b3)"
    },
    {
      "name": "ah_befujt_ch1",
      "type": "integer",
      "default_value": 0,
      "description": "Chamber 1: Supply absolute humidity \u00d71000"
    },
    {
      "name": "ah_cel_ch1",
      "type": "integer",
      "default_value": 0,
      "description": "Chamber 1: Target absolute humidity \u00d71000"
    },
    {
      "name": "dp_kamra_ch1",
      "type": "integer",
      "default_value": 0,
      "description": "Chamber 1: Chamber dew point \u00d710"
    },
    {
      "name": "dp_befujt_ch1",
      "type": "integer",
      "default_value": 0,
      "description": "Chamber 1: Supply dew point \u00d710"
    },
    {
      "name": "dp_cel_ch1",
      "type": "integer",
      "default_value": 0,
      "description": "Chamber 1: Target dew point \u00d710"
    },
    {
      "name": "ah_dp_table_ch1",
      "type": "string",
      "default_value": "{}",
      "description": "Chamber 1: AH/DP calculation cache"
    },
    {
      "name": "suly_meres_table_1_ch1",
      "type": "string",
      "default_value": "[]",
      "description": "Chamber 1: Weight sensor 1 buffer"
    },
    {
      "name": "suly_meres_table_2_ch1",
      "type": "string",
      "default_value": "[]",
      "description": "Chamber 1: Weight sensor 2 buffer"
    },
    {
      "name": "suly_meres_akt_1_ch1",
      "type": "integer",
      "default_value": 0,
      "description": "Chamber 1: Weight sensor 1 current"
    },
    {
      "name": "suly_meres_akt_2_ch1",
      "type": "integer",
      "default_value": 0,
      "description": "Chamber 1: Weight sensor 2 current"
    },
    {
      "name": "kamra_homerseklet_ch2",
      "type": "integer",
      "default_value": 0,
      "description": "Chamber 2: Chamber temperature \u00d710"
    },
    {
      "name": "kamra_para_ch2",
      "type": "integer",
      "default_value": 0,
      "description": "Chamber 2: Chamber humidity \u00d710"
    },
    {
      "name": "kamra_homerseklet_raw_ch2",
      "type": "integer",
      "default_value": 0,
      "description": "Chamber 2: Raw chamber temperature"
    },
    {
      "name": "kamra_para_raw_ch2",
      "type": "integer",
      "default_value": 0,
      "description": "Chamber 2: Raw chamber humidity"
    },
    {
      "name": "kamra_cel_homerseklet_ch2",
      "type": "integer",
      "default_value": 150,
      "description": "Chamber 2: Target chamber temp \u00d710 (15.0\u00b0C)"
    },
    {
      "name": "kamra_cel_para_ch2",
      "type": "integer",
      "default_value": 750,
      "description": "Chamber 2: Target chamber humidity \u00d710 (75.0%)"
    },
    {
      "name": "befujt_cel_homerseklet_ch2",
      "type": "integer",
      "default_value": 0,
      "description": "Chamber 2: Calculated supply air target temp"
    },
    {
      "name": "befujt_cel_para_ch2",
      "type": "integer",
      "default_value": 0,
      "description": "Chamber 2: Calculated supply air target humidity"
    },
    {
      "name": "befujt_homerseklet_akt_ch2",
      "type": "integer",
      "default_value": 0,
      "description": "Chamber 2: Current supply air temp"
    },
    {
      "name": "befujt_para_akt_ch2",
      "type": "integer",
      "default_value": 0,
      "description": "Chamber 2: Current supply air humidity"
    },
    {
      "name": "befujt_homerseklet_raw_ch2",
      "type": "integer",
      "default_value": 0,
      "description": "Chamber 2: Raw supply air temperature"
    },
    {
      "name": "befujt_para_raw_ch2",
      "type": "integer",
      "default_value": 0,
      "description": "Chamber 2: Raw supply air humidity"
    },
    {
      "name": "befujt_homerseklet_table_ch2",
      "type": "string",
      "default_value": "[]",
      "description": "Chamber 2: Supply air temp buffer"
    },
    {
      "name": "befujt_para_table_ch2",
      "type": "string",
      "default_value": "[]",
      "description": "Chamber 2: Supply air humidity buffer"
    },
    {
      "name": "kamra_homerseklet_table_ch2",
      "type": "string",
      "default_value": "[]",
      "description": "Chamber 2: Chamber temp buffer"
    },
    {
      "name": "kamra_para_table_ch2",
      "type": "string",
      "default_value": "[]",
      "description": "Chamber 2: Chamber humidity buffer"
    },
    {
      "name": "befujt_hibaszam_ch2",
      "type": "integer",
      "default_value": 10,
      "description": "Chamber 2: Supply sensor error count"
    },
    {
      "name": "kamra_hibaszam_ch2",
      "type": "integer",
      "default_value": 10,
      "description": "Chamber 2: Chamber sensor error count"
    },
    {
      "name": "constansok_ch2",
      "type": "string",
      "default_value": "{\"deltahi_kamra_homerseklet\":15,\"deltalo_kamra_homerseklet\":10,\"temp_hysteresis_kamra\":5,\"ah_deadzone_kamra\":80,\"ah_hysteresis_kamra\":30,\"deltahi_befujt_homerseklet\":10,\"deltalo_befujt_homerseklet\":10,\"temp_hysteresis_befujt\":3,\"ah_deadzone_befujt\":50,\"ah_hysteresis_befujt\":20,\"outdoor_mix_ratio\":30,\"outdoor_use_threshold\":50,\"proportional_gain\":10,\"min_supply_air_temp\":60,\"max_supply_air_temp\":400,\"min_temp_no_humidifier\":110,\"buffer_size\":5,\"spike_threshold\":50,\"max_error_count\":10,\"temp_change_threshold\":2,\"humidity_change_threshold\":5,\"humidifier_installed\":false,\"humidifier_start_delta\":50,\"sleep_cycle_enabled\":false,\"sleep_on_minutes\":45,\"sleep_off_minutes\":15,\"init_duration\":32}",
      "description": "Chamber 2: Control constants JSON (v2.5)"
    },
    {
      "name": "signals_ch2",
      "type": "string",
      "default_value": "{}",
      "description": "Chamber 2: Control signals state"
    },
    {
      "name": "cycle_variable_ch2",
      "type": "string",
      "default_value": "{\"aktiv\":true}",
      "description": "Chamber 2: Cycle state"
    },
    {
      "name": "ah_kamra_ch2",
      "type": "integer",
      "default_value": 0,
      "description": "Chamber 2: Chamber absolute humidity \u00d71000 (mg/m\u00b3)"
    },
    {
      "name": "ah_befujt_ch2",
      "type": "integer",
      "default_value": 0,
      "description": "Chamber 2: Supply absolute humidity \u00d71000"
    },
    {
      "name": "ah_cel_ch2",
      "type": "integer",
      "default_value": 0,
      "description": "Chamber 2: Target absolute humidity \u00d71000"
    },
    {
      "name": "dp_kamra_ch2",
      "type": "integer",
      "default_value": 0,
      "description": "Chamber 2: Chamber dew point \u00d710"
    },
    {
      "name": "dp_befujt_ch2",
      "type": "integer",
      "default_value": 0,
      "description": "Chamber 2: Supply dew point \u00d710"
    },
    {
      "name": "dp_cel_ch2",
      "type": "integer",
      "default_value": 0,
      "description": "Chamber 2: Target dew point \u00d710"
    },
    {
      "name": "ah_dp_table_ch2",
      "type": "string",
      "default_value": "{}",
      "description": "Chamber 2: AH/DP calculation cache"
    },
    {
      "name": "suly_meres_table_1_ch2",
      "type": "string",
      "default_value": "[]",
      "description": "Chamber 2: Weight sensor 1 buffer"
    },
    {
      "name": "suly_meres_table_2_ch2",
      "type": "string",
      "default_value": "[]",
      "description": "Chamber 2: Weight sensor 2 buffer"
    },
    {
      "name": "suly_meres_akt_1_ch2",
      "type": "integer",
      "default_value": 0,
      "description": "Chamber 2: Weight sensor 1 current"
    },
    {
      "name": "suly_meres_akt_2_ch2",
      "type": "integer",
      "default_value": 0,
      "description": "Chamber 2: Weight sensor 2 current"
    },
    {
      "name": "kulso_homerseklet_glbl",
      "type": "integer",
      "default_value": 0,
      "description": "Global: Outdoor temperature \u00d710"
    },
    {
      "name": "kulso_para_glbl",
      "type": "integer",
      "default_value": 0,
      "description": "Global: Outdoor humidity \u00d710"
    },
    {
      "name": "kulso_homerseklet_raw_glbl",
      "type": "integer",
      "default_value": 0,
      "description": "Global: Raw outdoor temperature"
    },
    {
      "name": "kulso_para_raw_glbl",
      "type": "integer",
      "default_value": 0,
      "description": "Global: Raw outdoor humidity"
    },
    {
      "name": "kulso_homerseklet_table_glbl",
      "type": "string",
      "default_value": "[]",
      "description": "Global: Outdoor temp buffer"
    },
    {
      "name": "kulso_para_table_glbl",
      "type": "string",
      "default_value": "[]",
      "description": "Global: Outdoor humidity buffer"
    },
    {
      "name": "kulso_ah_dp_glbl",
      "type": "string",
      "default_value": "{}",
      "description": "Global: Outdoor AH and dew point"
    },
    {
      "name": "kulso_hibaszam_glbl",
      "type": "integer",
      "default_value": 10,
      "description": "Global: Outdoor sensor error count"
    },
    {
      "name": "variable_name_map_glbl",
      "type": "string",
      "default_value": "{}",
      "description": "Global: Variable name to ID mapping"
    }
  ]
}